{
	"_t": "lib",
	"type_collection_names": [
		"win32"
	],
	"library_names": [
		"oledlg.dll"
	],
	"default_cc": {
		"X86": "SimCCStdcall",
		"AMD64": "SimCCMicrosoftAMD64"
	},
	"functions": {
		"OleUIAddVerbMenuA": {
			"proto": "{'_t': 'func', 'args': [{'_t': '_ref', 'name': 'IOleObject', 'ot': 'bot'}, {'_t': '_ref', 'name': 'PSTR', 'ot': 'ptr'}, {'_t': '_ref', 'name': 'HMENU', 'ot': 'ptr'}, {'_t': 'int', 'signed': false, 'label': 'UInt32'}, {'_t': 'int', 'signed': false, 'label': 'UInt32'}, {'_t': 'int', 'signed': false, 'label': 'UInt32'}, {'_t': '_ref', 'name': 'BOOL', 'ot': 'int'}, {'_t': 'int', 'signed': false, 'label': 'UInt32'}, {'_t': 'ptr', 'pts_to': {'_t': '_ref', 'name': 'HMENU', 'ot': '_ref'}}], 'returnty': {'_t': '_ref', 'name': 'BOOL', 'ot': 'int'}, 'arg_names': ['lpOleObj', 'lpszShortType', 'hMenu', 'uPos', 'uIDVerbMin', 'uIDVerbMax', 'bAddConvert', 'idConvert', 'lphMenu']}"
		},
		"OleUIAddVerbMenuW": {
			"proto": "{'_t': 'func', 'args': [{'_t': '_ref', 'name': 'IOleObject', 'ot': 'bot'}, {'_t': '_ref', 'name': 'PWSTR', 'ot': 'ptr'}, {'_t': '_ref', 'name': 'HMENU', 'ot': 'ptr'}, {'_t': 'int', 'signed': false, 'label': 'UInt32'}, {'_t': 'int', 'signed': false, 'label': 'UInt32'}, {'_t': 'int', 'signed': false, 'label': 'UInt32'}, {'_t': '_ref', 'name': 'BOOL', 'ot': 'int'}, {'_t': 'int', 'signed': false, 'label': 'UInt32'}, {'_t': 'ptr', 'pts_to': {'_t': '_ref', 'name': 'HMENU', 'ot': '_ref'}}], 'returnty': {'_t': '_ref', 'name': 'BOOL', 'ot': 'int'}, 'arg_names': ['lpOleObj', 'lpszShortType', 'hMenu', 'uPos', 'uIDVerbMin', 'uIDVerbMax', 'bAddConvert', 'idConvert', 'lphMenu']}"
		},
		"OleUIBusyA": {
			"proto": "{'_t': 'func', 'args': [{'_t': 'ptr', 'pts_to': {'_t': '_ref', 'name': 'OLEUIBUSYA', 'ot': '_ref'}}], 'returnty': {'_t': 'int', 'signed': false, 'label': 'UInt32'}, 'arg_names': ['param0']}"
		},
		"OleUIBusyW": {
			"proto": "{'_t': 'func', 'args': [{'_t': 'ptr', 'pts_to': {'_t': '_ref', 'name': 'OLEUIBUSYW', 'ot': '_ref'}}], 'returnty': {'_t': 'int', 'signed': false, 'label': 'UInt32'}, 'arg_names': ['param0']}"
		},
		"OleUICanConvertOrActivateAs": {
			"proto": "{'_t': 'func', 'args': [{'_t': 'ptr', 'pts_to': {'_t': 'bot', 'label': 'Guid'}}, {'_t': '_ref', 'name': 'BOOL', 'ot': 'int'}, {'_t': 'short', 'signed': false, 'label': 'UInt16'}], 'returnty': {'_t': '_ref', 'name': 'BOOL', 'ot': 'int'}, 'arg_names': ['rClsid', 'fIsLinkedObject', 'wFormat']}"
		},
		"OleUIChangeIconA": {
			"proto": "{'_t': 'func', 'args': [{'_t': 'ptr', 'pts_to': {'_t': '_ref', 'name': 'OLEUICHANGEICONA', 'ot': '_ref'}}], 'returnty': {'_t': 'int', 'signed': false, 'label': 'UInt32'}, 'arg_names': ['param0']}"
		},
		"OleUIChangeIconW": {
			"proto": "{'_t': 'func', 'args': [{'_t': 'ptr', 'pts_to': {'_t': '_ref', 'name': 'OLEUICHANGEICONW', 'ot': '_ref'}}], 'returnty': {'_t': 'int', 'signed': false, 'label': 'UInt32'}, 'arg_names': ['param0']}"
		},
		"OleUIChangeSourceA": {
			"proto": "{'_t': 'func', 'args': [{'_t': 'ptr', 'pts_to': {'_t': '_ref', 'name': 'OLEUICHANGESOURCEA', 'ot': '_ref'}}], 'returnty': {'_t': 'int', 'signed': false, 'label': 'UInt32'}, 'arg_names': ['param0']}"
		},
		"OleUIChangeSourceW": {
			"proto": "{'_t': 'func', 'args': [{'_t': 'ptr', 'pts_to': {'_t': '_ref', 'name': 'OLEUICHANGESOURCEW', 'ot': '_ref'}}], 'returnty': {'_t': 'int', 'signed': false, 'label': 'UInt32'}, 'arg_names': ['param0']}"
		},
		"OleUIConvertA": {
			"proto": "{'_t': 'func', 'args': [{'_t': 'ptr', 'pts_to': {'_t': '_ref', 'name': 'OLEUICONVERTA', 'ot': '_ref'}}], 'returnty': {'_t': 'int', 'signed': false, 'label': 'UInt32'}, 'arg_names': ['param0']}"
		},
		"OleUIConvertW": {
			"proto": "{'_t': 'func', 'args': [{'_t': 'ptr', 'pts_to': {'_t': '_ref', 'name': 'OLEUICONVERTW', 'ot': '_ref'}}], 'returnty': {'_t': 'int', 'signed': false, 'label': 'UInt32'}, 'arg_names': ['param0']}"
		},
		"OleUIEditLinksA": {
			"proto": "{'_t': 'func', 'args': [{'_t': 'ptr', 'pts_to': {'_t': '_ref', 'name': 'OLEUIEDITLINKSA', 'ot': '_ref'}}], 'returnty': {'_t': 'int', 'signed': false, 'label': 'UInt32'}, 'arg_names': ['param0']}"
		},
		"OleUIEditLinksW": {
			"proto": "{'_t': 'func', 'args': [{'_t': 'ptr', 'pts_to': {'_t': '_ref', 'name': 'OLEUIEDITLINKSW', 'ot': '_ref'}}], 'returnty': {'_t': 'int', 'signed': false, 'label': 'UInt32'}, 'arg_names': ['param0']}"
		},
		"OleUIInsertObjectA": {
			"proto": "{'_t': 'func', 'args': [{'_t': 'ptr', 'pts_to': {'_t': '_ref', 'name': 'OLEUIINSERTOBJECTA', 'ot': '_ref'}}], 'returnty': {'_t': 'int', 'signed': false, 'label': 'UInt32'}, 'arg_names': ['param0']}"
		},
		"OleUIInsertObjectW": {
			"proto": "{'_t': 'func', 'args': [{'_t': 'ptr', 'pts_to': {'_t': '_ref', 'name': 'OLEUIINSERTOBJECTW', 'ot': '_ref'}}], 'returnty': {'_t': 'int', 'signed': false, 'label': 'UInt32'}, 'arg_names': ['param0']}"
		},
		"OleUIObjectPropertiesA": {
			"proto": "{'_t': 'func', 'args': [{'_t': 'ptr', 'pts_to': {'_t': '_ref', 'name': 'OLEUIOBJECTPROPSA', 'ot': '_ref'}}], 'returnty': {'_t': 'int', 'signed': false, 'label': 'UInt32'}, 'arg_names': ['param0']}"
		},
		"OleUIObjectPropertiesW": {
			"proto": "{'_t': 'func', 'args': [{'_t': 'ptr', 'pts_to': {'_t': '_ref', 'name': 'OLEUIOBJECTPROPSW', 'ot': '_ref'}}], 'returnty': {'_t': 'int', 'signed': false, 'label': 'UInt32'}, 'arg_names': ['param0']}"
		},
		"OleUIPasteSpecialA": {
			"proto": "{'_t': 'func', 'args': [{'_t': 'ptr', 'pts_to': {'_t': '_ref', 'name': 'OLEUIPASTESPECIALA', 'ot': '_ref'}}], 'returnty': {'_t': 'int', 'signed': false, 'label': 'UInt32'}, 'arg_names': ['param0']}"
		},
		"OleUIPasteSpecialW": {
			"proto": "{'_t': 'func', 'args': [{'_t': 'ptr', 'pts_to': {'_t': '_ref', 'name': 'OLEUIPASTESPECIALW', 'ot': '_ref'}}], 'returnty': {'_t': 'int', 'signed': false, 'label': 'UInt32'}, 'arg_names': ['param0']}"
		},
		"OleUIPromptUserA": {
			"proto": "{'_t': 'func', 'args': [{'_t': 'int', 'label': 'Int32'}, {'_t': '_ref', 'name': 'HWND', 'ot': 'ptr'}], 'returnty': {'_t': 'int', 'label': 'Int32'}, 'arg_names': ['nTemplate', 'hwndParent']}"
		},
		"OleUIPromptUserW": {
			"proto": "{'_t': 'func', 'args': [{'_t': 'int', 'label': 'Int32'}, {'_t': '_ref', 'name': 'HWND', 'ot': 'ptr'}], 'returnty': {'_t': 'int', 'label': 'Int32'}, 'arg_names': ['nTemplate', 'hwndParent']}"
		},
		"OleUIUpdateLinksA": {
			"proto": "{'_t': 'func', 'args': [{'_t': '_ref', 'name': 'IOleUILinkContainerA', 'ot': 'bot'}, {'_t': '_ref', 'name': 'HWND', 'ot': 'ptr'}, {'_t': '_ref', 'name': 'PSTR', 'ot': 'ptr'}, {'_t': 'int', 'label': 'Int32'}], 'returnty': {'_t': '_ref', 'name': 'BOOL', 'ot': 'int'}, 'arg_names': ['lpOleUILinkCntr', 'hwndParent', 'lpszTitle', 'cLinks']}"
		},
		"OleUIUpdateLinksW": {
			"proto": "{'_t': 'func', 'args': [{'_t': '_ref', 'name': 'IOleUILinkContainerW', 'ot': 'bot'}, {'_t': '_ref', 'name': 'HWND', 'ot': 'ptr'}, {'_t': '_ref', 'name': 'PWSTR', 'ot': 'ptr'}, {'_t': 'int', 'label': 'Int32'}], 'returnty': {'_t': '_ref', 'name': 'BOOL', 'ot': 'int'}, 'arg_names': ['lpOleUILinkCntr', 'hwndParent', 'lpszTitle', 'cLinks']}"
		}
	}
}