{
    "type_collection_names": [
        "win32"
    ],
    "library_names": [
        "xpsprint.dll"
    ],
    "default_cc": {
        "X86": "SimCCStdcall",
        "AMD64": "SimCCMicrosoftAMD64"
    },
    "functions": {
        "StartXpsPrintJob": {
            "proto": {
                "__type__": "SimTypeFunction",
                "args": [
                    {
                        "__type__": "SimTypePointer",
                        "pts_to": {
                            "__type__": "SimTypeChar",
                            "signed": true,
                            "label": "Char"
                        },
                        "label": null,
                        "offset": 0
                    },
                    {
                        "__type__": "SimTypePointer",
                        "pts_to": {
                            "__type__": "SimTypeChar",
                            "signed": true,
                            "label": "Char"
                        },
                        "label": null,
                        "offset": 0
                    },
                    {
                        "__type__": "SimTypePointer",
                        "pts_to": {
                            "__type__": "SimTypeChar",
                            "signed": true,
                            "label": "Char"
                        },
                        "label": null,
                        "offset": 0
                    },
                    {
                        "__type__": "SimTypePointer",
                        "pts_to": {
                            "__type__": "SimTypeInt",
                            "signed": true,
                            "label": "Int"
                        },
                        "label": "IntPtr",
                        "offset": 0
                    },
                    {
                        "__type__": "SimTypePointer",
                        "pts_to": {
                            "__type__": "SimTypeInt",
                            "signed": true,
                            "label": "Int"
                        },
                        "label": "IntPtr",
                        "offset": 0
                    },
                    {
                        "__type__": "SimTypePointer",
                        "pts_to": {
                            "__type__": "SimTypeChar",
                            "signed": false,
                            "label": "Byte"
                        },
                        "label": "LPArray",
                        "offset": 0
                    },
                    {
                        "__type__": "SimTypeInt",
                        "signed": false,
                        "label": "UInt32"
                    },
                    {
                        "__type__": "SimTypePointer",
                        "pts_to": {
                            "__type__": "SimTypeBottom",
                            "label": "IXpsPrintJob"
                        },
                        "label": null,
                        "offset": 0
                    },
                    {
                        "__type__": "SimTypePointer",
                        "pts_to": {
                            "__type__": "SimTypeBottom",
                            "label": "IXpsPrintJobStream"
                        },
                        "label": null,
                        "offset": 0
                    },
                    {
                        "__type__": "SimTypePointer",
                        "pts_to": {
                            "__type__": "SimTypeBottom",
                            "label": "IXpsPrintJobStream"
                        },
                        "label": null,
                        "offset": 0
                    }
                ],
                "returnty": {
                    "__type__": "SimTypeInt",
                    "signed": true,
                    "label": "Int32"
                },
                "label": null,
                "arg_names": [
                    "printerName",
                    "jobName",
                    "outputFileName",
                    "progressEvent",
                    "completionEvent",
                    "printablePagesOn",
                    "printablePagesOnCount",
                    "xpsPrintJob",
                    "documentStream",
                    "printTicketStream"
                ],
                "variadic": false
            },
            "doc": ""
        },
        "StartXpsPrintJob1": {
            "proto": {
                "__type__": "SimTypeFunction",
                "args": [
                    {
                        "__type__": "SimTypePointer",
                        "pts_to": {
                            "__type__": "SimTypeChar",
                            "signed": true,
                            "label": "Char"
                        },
                        "label": null,
                        "offset": 0
                    },
                    {
                        "__type__": "SimTypePointer",
                        "pts_to": {
                            "__type__": "SimTypeChar",
                            "signed": true,
                            "label": "Char"
                        },
                        "label": null,
                        "offset": 0
                    },
                    {
                        "__type__": "SimTypePointer",
                        "pts_to": {
                            "__type__": "SimTypeChar",
                            "signed": true,
                            "label": "Char"
                        },
                        "label": null,
                        "offset": 0
                    },
                    {
                        "__type__": "SimTypePointer",
                        "pts_to": {
                            "__type__": "SimTypeInt",
                            "signed": true,
                            "label": "Int"
                        },
                        "label": "IntPtr",
                        "offset": 0
                    },
                    {
                        "__type__": "SimTypePointer",
                        "pts_to": {
                            "__type__": "SimTypeInt",
                            "signed": true,
                            "label": "Int"
                        },
                        "label": "IntPtr",
                        "offset": 0
                    },
                    {
                        "__type__": "SimTypePointer",
                        "pts_to": {
                            "__type__": "SimTypeBottom",
                            "label": "IXpsPrintJob"
                        },
                        "label": null,
                        "offset": 0
                    },
                    {
                        "__type__": "SimTypePointer",
                        "pts_to": {
                            "__type__": "SimTypeBottom",
                            "label": "IXpsOMPackageTarget"
                        },
                        "label": null,
                        "offset": 0
                    }
                ],
                "returnty": {
                    "__type__": "SimTypeInt",
                    "signed": true,
                    "label": "Int32"
                },
                "label": null,
                "arg_names": [
                    "printerName",
                    "jobName",
                    "outputFileName",
                    "progressEvent",
                    "completionEvent",
                    "xpsPrintJob",
                    "printContentReceiver"
                ],
                "variadic": false
            },
            "doc": ""
        }
    }
}